{"_type":"export","__export_format":4,"__export_date":"2020-10-30T12:53:53.891Z","__export_source":"insomnia.desktop.app:v2020.4.2","resources":[{"_id":"req_fc125c0c2df94388a4edb3f311799f19","parentId":"wrk_ec97d8daab104b22b71d510689304add","modified":1604062186790,"created":1604003634875,"url":"https://api.twitter.com/2/tweets/1275828087666679809","name":"Tweet Lookup","description":"","method":"GET","body":{},"parameters":[],"headers":[],"authentication":{"type":"oauth1","disabled":false,"signatureMethod":"HMAC-SHA1","consumerKey":"{{ TWITTER_KEY }}","consumerSecret":"{{ TWITTER_SECRET_KEY }}","tokenKey":"{{ TWITTER_TOKEN }}","tokenSecret":"{{ TWITTER_SECRET_TOKEN }}","privateKey":"","version":"1.0","nonce":"","timestamp":"","callback":"","includeBodyHash":false},"metaSortKey":-1604003634875,"isPrivate":false,"settingStoreCookies":true,"settingSendCookies":true,"settingDisableRenderRequestBody":false,"settingEncodeUrl":true,"settingRebuildPath":true,"settingFollowRedirects":"global","_type":"request"},{"_id":"wrk_ec97d8daab104b22b71d510689304add","parentId":null,"modified":1604002995565,"created":1604002995565,"name":"Udemy-RESTAPIAWRESTANTN1","description":"","scope":null,"_type":"workspace"},{"_id":"req_f25c9a0baec344b4b9e13e1106e027db","parentId":"wrk_ec97d8daab104b22b71d510689304add","modified":1604062355117,"created":1604062151048,"url":"https://api.twitter.com/1.1/statuses/update.json","name":"Update","description":"","method":"POST","body":{},"parameters":[{"name":"status","value":"teste","description":"","id":"pair_4fd5516579eb45c6b8f012929eb5aec1"}],"headers":[],"authentication":{"type":"oauth1","disabled":false,"signatureMethod":"HMAC-SHA1","consumerKey":"{{ TWITTER_KEY }}","consumerSecret":"{{ TWITTER_SECRET_KEY }}","tokenKey":"{{ TWITTER_TOKEN }}","tokenSecret":"{{ TWITTER_SECRET_TOKEN }}","privateKey":"","version":"1.0","nonce":"","timestamp":"","callback":"","includeBodyHash":false},"metaSortKey":-1602996581740,"isPrivate":false,"settingStoreCookies":true,"settingSendCookies":true,"settingDisableRenderRequestBody":false,"settingEncodeUrl":true,"settingRebuildPath":true,"settingFollowRedirects":"global","_type":"request"},{"_id":"env_942d041967f2e0b56d3e198bebb43c897673b70c","parentId":"wrk_ec97d8daab104b22b71d510689304add","modified":1604005973157,"created":1604002995637,"name":"Base Environment","data":{},"dataPropertyOrder":{},"color":null,"isPrivate":false,"metaSortKey":1604002995637,"_type":"environment"},{"_id":"jar_942d041967f2e0b56d3e198bebb43c897673b70c","parentId":"wrk_ec97d8daab104b22b71d510689304add","modified":1604062303314,"created":1604002995638,"name":"Default Jar","cookies":[{"key":"personalization_id","value":"\"v1_azVopIXrB6iei4joKewkkQ==\"","expires":"2022-10-29T20:34:17.000Z","maxAge":63072000,"domain":"twitter.com","path":"/","secure":true,"extensions":["SameSite=None"],"hostOnly":false,"creation":"2020-10-29T20:34:17.266Z","lastAccessed":"2020-10-29T20:34:17.266Z","id":"5375735472221383"},{"key":"guest_id","value":"v1%3A160400365716877113","expires":"2022-10-29T20:34:17.000Z","maxAge":63072000,"domain":"twitter.com","path":"/","secure":true,"extensions":["SameSite=None"],"hostOnly":false,"creation":"2020-10-29T20:34:17.267Z","lastAccessed":"2020-10-29T20:34:17.267Z","id":"3706543124617705"},{"key":"lang","value":"pt","domain":"api.twitter.com","path":"/","hostOnly":true,"creation":"2020-10-30T12:51:43.280Z","lastAccessed":"2020-10-30T12:51:43.280Z","id":"44622440881892134"}],"_type":"cookie_jar"},{"_id":"spc_840ea6c3e5f64053bb80785042751689","parentId":"wrk_ec97d8daab104b22b71d510689304add","modified":1604002995575,"created":1604002995575,"fileName":"Udemy-RESTAPIAWRESTANTN1","contents":"","contentType":"yaml","_type":"api_spec"}]}